[
  {
    "id": 19076,
    "name": "12B Ginseng Linzhi Hộp 10 Vỉ X 10 Viên Nang Mềm Vinaphar",
    "common_name": null,
    "images": [
      "image/z5436426695858_d4015c4c1f99f5f65762520f84ce30af1715593869.jpg"
    ],
    "price": 45500,
    "order_up": 0,
    "price_2": 0,
    "retail_price": 0,
    "profit_percent": 10.7143,
    "suggest_web_price": 45500,
    "suggest_price": null,
    "min_invent": null,
    "est_imp": 0,
    "category_id": 33,
    "producer_id": 286,
    "weight": 0,
    "dv_id": null,
    "area_id": 2,
    "min_quantity": null,
    "note": null,
    "note_other": "",
    "status": "OK",
    "web_show": "OK",
    "type": "COM",
    "classify": "hang_hoa",
    "buy_address": null,
    "web_promotion": "NO",
    "promotional_program": null,
    "web_price": "DEFAULT",
    "web_stock": "HAVE",
    "group": "GROUP1",
    "unit": "hộp",
    "web_volume": "hộp 10 vỉ x 10 viên",
    "date_expire": null,
    "time_lock": "2025-01-10 12:36:22",
    "substitutes": "[]",
    "created_at": null,
    "updated_at": "2025-03-12 00:02:02",
    "status_import": "OK",
    "old_price": 45500
  },
  {
    "id": 19072,
    "name": "12B Ginseng Linzhi Đông Trùng Hạ Thảo Hộp 10 Vỉ X 10 Viên Nang Vinaphar",
    "common_name": null,
    "images": [
      "image/z5436379373665_b5f0dd24faaeac6d68b3e6168ca57c7d1715593714.jpg"
    ],
    "price": 55000,
    "order_up": 0,
    "price_2": 0,
    "retail_price": 0,
    "profit_percent": 10,
    "suggest_web_price": 55000,
    "suggest_price": null,
    "min_invent": null,
    "est_imp": 0,
    "category_id": 33,
    "producer_id": 333,
    "weight": 0,
    "dv_id": null,
    "area_id": 4,
    "min_quantity": null,
    "note": null,
    "note_other": "",
    "status": "OK",
    "web_show": "OK",
    "type": "COM",
    "classify": "hang_hoa",
    "buy_address": null,
    "web_promotion": "NO",
    "promotional_program": null,
    "web_price": "DEFAULT",
    "web_stock": "HAVE",
    "group": "GROUP1",
    "unit": "Hộp",
    "web_volume": "hộp 10 vỉ x 10 viên",
    "date_expire": null,
    "time_lock": "2025-01-11 08:47:54",
    "substitutes": "[]",
    "created_at": null,
    "updated_at": "2025-03-12 08:47:54",
    "status_import": "OK",
    "old_price": 55000
  },
  {
    "id": 19078,
    "name": "18B Ginseng Linzhi Nhung Hươu Sữa Ong Chúa Hộp 10 Vỉ X 10 Viên Nang Mềm Vinaphar",
    "common_name": null,
    "images": [
      "image/z5436465366563_7d4993845976eb9e323697f25f254a1f1715593955.jpg"
    ],
    "price": 55000,
    "order_up": 0,
    "price_2": 0,
    "retail_price": 0,
    "profit_percent": 10,
    "suggest_web_price": 55000,
    "suggest_price": null,
    "min_invent": null,
    "est_imp": 0,
    "category_id": 33,
    "producer_id": 333,
    "weight": 0,
    "dv_id": null,
    "area_id": 1,
    "min_quantity": null,
    "note": null,
    "note_other": "",
    "status": "OK",
    "web_show": "OK",
    "type": "COM",
    "classify": "hang_hoa",
    "buy_address": null,
    "web_promotion": "NO",
    "promotional_program": null,
    "web_price": "DEFAULT",
    "web_stock": "HAVE",
    "group": "GROUP1",
    "unit": "hộp",
    "web_volume": "hộp 10 vỉ x 10 viên",
    "date_expire": null,
    "time_lock": "2025-01-11 10:05:01",
    "substitutes": "[]",
    "created_at": null,
    "updated_at": "2025-03-12 10:05:01",
    "status_import": "OK",
    "old_price": 55000
  },
  {
    "id": 19395,
    "name": "20B Nấm Đông Trùng Hạ Thảo _Zn Hộp 100 Viên",
    "common_name": null,
    "images": ["image/NẤM ĐÔNG TRÙNG HẠ THẢO1721439946.jpg"],
    "price": 54000,
    "order_up": 0,
    "price_2": 0,
    "retail_price": 0,
    "profit_percent": 8,
    "suggest_web_price": 54000,
    "suggest_price": null,
    "min_invent": null,
    "est_imp": 0,
    "category_id": 29,
    "producer_id": null,
    "weight": 0,
    "dv_id": null,
    "area_id": 2,
    "min_quantity": null,
    "note": null,
    "note_other": "",
    "status": "OK",
    "web_show": "OK",
    "type": "COM",
    "classify": "hang_hoa",
    "buy_address": null,
    "web_promotion": null,
    "promotional_program": null,
    "web_price": null,
    "web_stock": null,
    "group": "GROUP1",
    "unit": "hộp",
    "web_volume": null,
    "date_expire": null,
    "time_lock": "2025-01-11 10:57:35",
    "substitutes": "[]",
    "created_at": null,
    "updated_at": "2025-03-12 10:57:34",
    "status_import": "OK",
    "old_price": 54000
  },
  {
    "id": 18244,
    "name": "3B Linhzhi Đông Trùng Hộp 10 Vỉ X 10 Viên",
    "common_name": null,
    "images": ["image/182441725677900.jpg"],
    "price": 34000,
    "order_up": 0,
    "price_2": 0,
    "retail_price": 0,
    "profit_percent": 17.2414,
    "suggest_web_price": 34000,
    "suggest_price": null,
    "min_invent": null,
    "est_imp": 0,
    "category_id": 29,
    "producer_id": 808,
    "weight": 0,
    "dv_id": null,
    "area_id": 4,
    "min_quantity": null,
    "note": null,
    "note_other": "",
    "status": "OK",
    "web_show": "OK",
    "type": "COM",
    "classify": "hang_hoa",
    "buy_address": null,
    "web_promotion": "NO",
    "promotional_program": null,
    "web_price": "DEFAULT",
    "web_stock": "HAVE",
    "group": "GROUP1",
    "unit": "hộp",
    "web_volume": null,
    "date_expire": null,
    "time_lock": "2025-01-10 12:05:55",
    "substitutes": "[]",
    "created_at": null,
    "updated_at": "2025-03-12 00:02:02",
    "status_import": "OK",
    "old_price": 34000
  },
  {
    "id": 18637,
    "name": "3B Lysine Hộp 100 Viên Nang Mềm Akofa",
    "common_name": null,
    "images": ["image/1031407abf0c12524b1d1708058299.jpg"],
    "price": 37500,
    "order_up": 0,
    "price_2": 0,
    "retail_price": 0,
    "profit_percent": 13.6364,
    "suggest_web_price": 37500,
    "suggest_price": null,
    "min_invent": null,
    "est_imp": 25,
    "category_id": 33,
    "producer_id": 501,
    "weight": 0,
    "dv_id": null,
    "area_id": 4,
    "min_quantity": null,
    "note": null,
    "note_other": "",
    "status": "OK",
    "web_show": "OK",
    "type": "COM",
    "classify": "hang_hoa",
    "buy_address": null,
    "web_promotion": "NO",
    "promotional_program": null,
    "web_price": "DEFAULT",
    "web_stock": "HAVE",
    "group": "GROUP1",
    "unit": "hộp",
    "web_volume": null,
    "date_expire": null,
    "time_lock": "2025-01-11 11:52:23",
    "substitutes": "[]",
    "created_at": null,
    "updated_at": "2025-03-12 11:52:23",
    "status_import": "OK",
    "old_price": 37500
  },
  {
    "id": 20370,
    "name": "3B Lysine, Linh Chi Đông Trùng Hộp 100 Viên (B1,B6,B12) Nang Mềm , Akopa - 3B Lysine",
    "common_name": null,
    "images": ["image/lysine1739180415.jpg"],
    "price": 30300,
    "order_up": 0,
    "price_2": 0,
    "retail_price": 0,
    "profit_percent": null,
    "suggest_web_price": null,
    "suggest_price": null,
    "min_invent": null,
    "est_imp": null,
    "category_id": null,
    "producer_id": null,
    "weight": 0,
    "dv_id": null,
    "area_id": 3,
    "min_quantity": null,
    "note": null,
    "note_other": "",
    "status": "OK",
    "web_show": "OK",
    "type": "COM",
    "classify": "hang_hoa",
    "buy_address": null,
    "web_promotion": null,
    "promotional_program": null,
    "web_price": null,
    "web_stock": null,
    "group": "GROUP1",
    "unit": "hộp",
    "web_volume": null,
    "date_expire": null,
    "time_lock": "2025-01-11 11:26:25",
    "substitutes": "[]",
    "created_at": null,
    "updated_at": "2025-03-12 11:26:23",
    "status_import": "OK",
    "old_price": 30300
  },
  {
    "id": 20091,
    "name": "3B Lysine, Linh Chi Đông Trùng Hộp100 Viên Nang Mềm , Akopa",
    "common_name": "3B Lysine",
    "images": ["image/lysin1732937946.jpg"],
    "price": 30300,
    "order_up": 0,
    "price_2": 0,
    "retail_price": 0,
    "profit_percent": null,
    "suggest_web_price": null,
    "suggest_price": null,
    "min_invent": null,
    "est_imp": null,
    "category_id": 33,
    "producer_id": 501,
    "weight": 0,
    "dv_id": null,
    "area_id": 2,
    "min_quantity": null,
    "note": null,
    "note_other": "",
    "status": "OK",
    "web_show": "OK",
    "type": "COM",
    "classify": "hang_hoa",
    "buy_address": null,
    "web_promotion": null,
    "promotional_program": null,
    "web_price": null,
    "web_stock": null,
    "group": "GROUP1",
    "unit": "hộp",
    "web_volume": "hộp 100 viên nang mềm",
    "date_expire": null,
    "time_lock": "2025-01-11 12:02:30",
    "substitutes": "[]",
    "created_at": null,
    "updated_at": "2025-03-12 12:02:30",
    "status_import": "OK",
    "old_price": 30300
  },
  {
    "id": 16876,
    "name": "5 - Mthf Multivitamin Plus Hộp 30 Viên Nang Quatrefolic Mỹ Có Dấu",
    "common_name": null,
    "images": ["image/plusss1723458224.jpg"],
    "price": 333000,
    "order_up": 0,
    "price_2": 0,
    "retail_price": 0,
    "profit_percent": 7.30159,
    "suggest_web_price": 333000,
    "suggest_price": null,
    "min_invent": null,
    "est_imp": 0,
    "category_id": 33,
    "producer_id": 302,
    "weight": 51,
    "dv_id": 2,
    "area_id": 1,
    "min_quantity": null,
    "note": null,
    "note_other": "",
    "status": "OK",
    "web_show": "OK",
    "type": "COM",
    "classify": "hang_hoa",
    "buy_address": "330",
    "web_promotion": "NO",
    "promotional_program": null,
    "web_price": "DEFAULT",
    "web_stock": "HAVE",
    "group": "GROUP1",
    "unit": "hộp",
    "web_volume": null,
    "date_expire": null,
    "time_lock": "2025-01-11 12:08:27",
    "substitutes": "[]",
    "created_at": null,
    "updated_at": "2025-03-12 12:08:26",
    "status_import": "OK",
    "old_price": 333000
  },
  {
    "id": 19070,
    "name": "9B Ginseng Linzhi Hộp 10 Vỉ X 10 Viên Nang Mềm Vinaphar",
    "common_name": null,
    "images": [
      "image/z5436362208454_cea8eee398a50159284171ac96afa54a1715593638.jpg"
    ],
    "price": 45500,
    "order_up": 0,
    "price_2": 0,
    "retail_price": 0,
    "profit_percent": 13.75,
    "suggest_web_price": 45500,
    "suggest_price": null,
    "min_invent": null,
    "est_imp": 0,
    "category_id": 33,
    "producer_id": 333,
    "weight": 0,
    "dv_id": null,
    "area_id": 3,
    "min_quantity": null,
    "note": null,
    "note_other": "",
    "status": "OK",
    "web_show": "OK",
    "type": "COM",
    "classify": "hang_hoa",
    "buy_address": null,
    "web_promotion": "NO",
    "promotional_program": null,
    "web_price": "DEFAULT",
    "web_stock": "HAVE",
    "group": "GROUP1",
    "unit": "Hộp",
    "web_volume": "Hộp 10 vỉ x 10 viên",
    "date_expire": null,
    "time_lock": "2025-03-11 17:31:00",
    "substitutes": "[]",
    "created_at": null,
    "updated_at": "2025-03-12 00:02:02",
    "status_import": "OK",
    "old_price": 45500
  },
  {
    "id": 9332,
    "name": "A.c Mexcold Paracetamol 325Mg Lọ 200 Viên Nang Cứng Agimexpharm",
    "common_name": null,
    "images": ["image/Capture1627960724.PNG"],
    "price": 110500,
    "order_up": 0,
    "price_2": 0,
    "retail_price": 0,
    "profit_percent": null,
    "suggest_web_price": 110000,
    "suggest_price": null,
    "min_invent": null,
    "est_imp": 0,
    "category_id": 27,
    "producer_id": 29,
    "weight": 120,
    "dv_id": null,
    "area_id": 1,
    "min_quantity": null,
    "note": null,
    "note_other": "",
    "status": "OK",
    "web_show": "OK",
    "type": "COM",
    "classify": "hang_hoa",
    "buy_address": "227",
    "web_promotion": "NO",
    "promotional_program": null,
    "web_price": "DEFAULT",
    "web_stock": "HAVE",
    "group": "GROUP1",
    "unit": "Lọ",
    "web_volume": "Lọ 200 viên",
    "date_expire": null,
    "time_lock": "2025-01-10 16:18:29",
    "substitutes": "[]",
    "created_at": "2021-08-03 04:34:22",
    "updated_at": "2025-03-12 00:02:02",
    "status_import": "OK",
    "old_price": 110500
  },
  {
    "id": 18454,
    "name": "A.t Alugela Hộp 26 Gói",
    "common_name": null,
    "images": ["image/AT1703555035.jpg"],
    "price": 47500,
    "order_up": 0,
    "price_2": 0,
    "retail_price": 0,
    "profit_percent": null,
    "suggest_web_price": null,
    "suggest_price": null,
    "min_invent": null,
    "est_imp": 0,
    "category_id": 34,
    "producer_id": 29,
    "weight": 560,
    "dv_id": null,
    "area_id": 1,
    "min_quantity": null,
    "note": null,
    "note_other": "",
    "status": "OK",
    "web_show": "OK",
    "type": "COM",
    "classify": "hang_hoa",
    "buy_address": null,
    "web_promotion": "NO",
    "promotional_program": null,
    "web_price": "DEFAULT",
    "web_stock": "HAVE",
    "group": "GROUP1",
    "unit": "hộp",
    "web_volume": null,
    "date_expire": null,
    "time_lock": "2025-01-11 11:11:54",
    "substitutes": "[]",
    "created_at": null,
    "updated_at": "2025-03-12 11:11:53",
    "status_import": "OK",
    "old_price": 47500
  },
  {
    "id": 5068,
    "name": "A.t Ambroxol 30Mg Hộp 30 Ống X 5Ml An Thiên",
    "common_name": "Ambroxol Ống",
    "images": ["image/amb o1624499604.jpg"],
    "price": 76000,
    "order_up": 0,
    "price_2": 0,
    "retail_price": 0,
    "profit_percent": 5.55556,
    "suggest_web_price": 76000,
    "suggest_price": null,
    "min_invent": null,
    "est_imp": 0,
    "category_id": 37,
    "producer_id": 29,
    "weight": 0,
    "dv_id": 5,
    "area_id": 2,
    "min_quantity": null,
    "note": null,
    "note_other": "",
    "status": "OK",
    "web_show": "OK",
    "type": "COM",
    "classify": "hang_hoa",
    "buy_address": "422",
    "web_promotion": "NO",
    "promotional_program": null,
    "web_price": "DEFAULT",
    "web_stock": "HAVE",
    "group": "GROUP1",
    "unit": "Hộp",
    "web_volume": "Hộp 30 ống",
    "date_expire": null,
    "time_lock": "2025-01-11 17:20:32",
    "substitutes": null,
    "created_at": "2021-06-20 13:02:53",
    "updated_at": "2025-03-12 17:20:32",
    "status_import": "OK",
    "old_price": 76000
  },
  {
    "id": 9333,
    "name": "A.t Ambroxol 30Mg Lọ 60Ml An Thiên",
    "common_name": "A.t Ambroxol",
    "images": [
      "image/00029076-ambroxol-30mg-an-thien-60ml-huong-cam-1735-609c_large1627958860.jpg"
    ],
    "price": 17800,
    "order_up": 0,
    "price_2": 0,
    "retail_price": 0,
    "profit_percent": 15.7498,
    "suggest_web_price": 17800,
    "suggest_price": null,
    "min_invent": null,
    "est_imp": 0,
    "category_id": 37,
    "producer_id": 29,
    "weight": 0,
    "dv_id": 7,
    "area_id": 3,
    "min_quantity": null,
    "note": null,
    "note_other": "",
    "status": "OK",
    "web_show": "OK",
    "type": "COM",
    "classify": "hang_hoa",
    "buy_address": null,
    "web_promotion": "NO",
    "promotional_program": null,
    "web_price": "DEFAULT",
    "web_stock": "HAVE",
    "group": "GROUP1",
    "unit": "Hộp",
    "web_volume": "Hộp 1 chai 60ml",
    "date_expire": "2026-05-20",
    "time_lock": "2025-01-11 14:54:24",
    "substitutes": null,
    "created_at": "2021-08-03 04:34:22",
    "updated_at": "2025-03-12 14:54:25",
    "status_import": "OK",
    "old_price": 17800
  },
  {
    "id": 9338,
    "name": "A.T Ascorbic siro lọ 60ml An Thiên",
    "common_name": null,
    "images": ["image/A.T-ASCORBIC-Syrup-600x6191627960865.png"],
    "price": 14300,
    "order_up": 0,
    "price_2": 0,
    "retail_price": 0,
    "profit_percent": null,
    "suggest_web_price": 17000,
    "suggest_price": null,
    "min_invent": null,
    "est_imp": 0,
    "category_id": 33,
    "producer_id": 29,
    "weight": 147,
    "dv_id": 10,
    "area_id": 2,
    "min_quantity": null,
    "note": null,
    "note_other": "",
    "status": "OK",
    "web_show": "OK",
    "type": "COM",
    "classify": "hang_hoa",
    "buy_address": null,
    "web_promotion": "NO",
    "promotional_program": null,
    "web_price": "DEFAULT",
    "web_stock": "HAVE",
    "group": "GROUP1",
    "unit": "Chai",
    "web_volume": "Chai 60ml",
    "date_expire": "2026-07-07",
    "time_lock": "2025-01-09 15:23:04",
    "substitutes": null,
    "created_at": "2021-08-03 04:34:22",
    "updated_at": "2025-03-12 00:02:02",
    "status_import": "OK",
    "old_price": 14300
  },
  {
    "id": 5089,
    "name": "A.t Ascorbic Vitamin C 100Mg/5Ml Hộp 30 Ống X 10Ml An Thiên",
    "common_name": "Ascorbic Ống An Thiên",
    "images": ["image/at-ascorbic-5ml-hop-30ong-2-700x4671625245672.jpg"],
    "price": 70500,
    "order_up": 0,
    "price_2": 0,
    "retail_price": 0,
    "profit_percent": null,
    "suggest_web_price": 82000,
    "suggest_price": null,
    "min_invent": null,
    "est_imp": 0,
    "category_id": 33,
    "producer_id": 29,
    "weight": 0,
    "dv_id": 11,
    "area_id": 2,
    "min_quantity": null,
    "note": null,
    "note_other": "",
    "status": "OK",
    "web_show": "OK",
    "type": "COM",
    "classify": "hang_hoa",
    "buy_address": null,
    "web_promotion": "NO",
    "promotional_program": null,
    "web_price": "DEFAULT",
    "web_stock": "HAVE",
    "group": "GROUP1",
    "unit": "Hộp",
    "web_volume": "Hộp 30 ống",
    "date_expire": "2026-09-01",
    "time_lock": "2025-01-11 11:53:13",
    "substitutes": "[]",
    "created_at": "2021-06-20 13:02:53",
    "updated_at": "2025-03-12 11:53:13",
    "status_import": "OK",
    "old_price": 70500
  },
  {
    "id": 18566,
    "name": "A.t Calmax 456Mg/426Mg Hộp 30 Ống X 10Ml An Thiên",
    "common_name": null,
    "images": ["image/e3a7d300aeab05f55cba1705628121.jpg"],
    "price": 68000,
    "order_up": 0,
    "price_2": 0,
    "retail_price": 0,
    "profit_percent": null,
    "suggest_web_price": null,
    "suggest_price": null,
    "min_invent": null,
    "est_imp": 0,
    "category_id": 33,
    "producer_id": 29,
    "weight": 0,
    "dv_id": null,
    "area_id": 4,
    "min_quantity": null,
    "note": null,
    "note_other": "",
    "status": "OK",
    "web_show": "OK",
    "type": "COM",
    "classify": "hang_hoa",
    "buy_address": null,
    "web_promotion": "NO",
    "promotional_program": null,
    "web_price": "DEFAULT",
    "web_stock": "HAVE",
    "group": "GROUP1",
    "unit": "hộp",
    "web_volume": null,
    "date_expire": null,
    "time_lock": "2025-01-09 13:10:34",
    "substitutes": "[]",
    "created_at": null,
    "updated_at": "2025-03-12 00:02:02",
    "status_import": "OK",
    "old_price": 68000
  },
  {
    "id": 5173,
    "name": "A.T Calmax Calcium Lactat 500mg hộp 30 ống x 10ml An Thiên",
    "common_name": "Calci Ống Nhựa",
    "images": ["image/at cal1624506744.jpg"],
    "price": 73000,
    "order_up": 0,
    "price_2": 0,
    "retail_price": 0,
    "profit_percent": null,
    "suggest_web_price": 68000,
    "suggest_price": null,
    "min_invent": null,
    "est_imp": 0,
    "category_id": 33,
    "producer_id": 29,
    "weight": 0,
    "dv_id": 13,
    "area_id": 3,
    "min_quantity": null,
    "note": null,
    "note_other": "",
    "status": "OK",
    "web_show": "OK",
    "type": "COM",
    "classify": "hang_hoa",
    "buy_address": "422",
    "web_promotion": "NO",
    "promotional_program": null,
    "web_price": "DEFAULT",
    "web_stock": "HAVE",
    "group": "GROUP1",
    "unit": "Hộp",
    "web_volume": "Hộp 30 ống",
    "date_expire": "2026-07-01",
    "time_lock": "2025-01-03 19:54:08",
    "substitutes": null,
    "created_at": "2021-06-20 13:02:53",
    "updated_at": "2025-03-12 00:02:02",
    "status_import": "OK",
    "old_price": 73000
  },
  {
    "id": 19458,
    "name": "A.t Cetam 400Mg Hộp 30 Ống X 10 Ml - An Thiên",
    "common_name": null,
    "images": ["image/cetam1722480435.jpg"],
    "price": 96000,
    "order_up": 0,
    "price_2": 0,
    "retail_price": 0,
    "profit_percent": null,
    "suggest_web_price": null,
    "suggest_price": null,
    "min_invent": null,
    "est_imp": 0,
    "category_id": 31,
    "producer_id": 29,
    "weight": 0,
    "dv_id": null,
    "area_id": 2,
    "min_quantity": null,
    "note": null,
    "note_other": "",
    "status": "OK",
    "web_show": "OK",
    "type": "COM",
    "classify": "hang_hoa",
    "buy_address": null,
    "web_promotion": null,
    "promotional_program": null,
    "web_price": null,
    "web_stock": null,
    "group": "GROUP1",
    "unit": "Hộp",
    "web_volume": null,
    "date_expire": null,
    "time_lock": "2025-01-04 10:23:52",
    "substitutes": "[]",
    "created_at": null,
    "updated_at": "2025-03-12 00:02:02",
    "status_import": "OK",
    "old_price": 96000
  },
  {
    "id": 18529,
    "name": "A.t Desloratadin 2,5Mg Hộp 30 Gói X 5Ml An Thiên",
    "common_name": null,
    "images": ["image/22d77673f6a05dfe04b11705029825.jpg"],
    "price": 53000,
    "order_up": 0,
    "price_2": 0,
    "retail_price": 0,
    "profit_percent": 10.4167,
    "suggest_web_price": 53000,
    "suggest_price": null,
    "min_invent": null,
    "est_imp": 0,
    "category_id": 37,
    "producer_id": 29,
    "weight": 0,
    "dv_id": null,
    "area_id": 2,
    "min_quantity": null,
    "note": null,
    "note_other": "",
    "status": "OK",
    "web_show": "OK",
    "type": "COM",
    "classify": "hang_hoa",
    "buy_address": null,
    "web_promotion": "NO",
    "promotional_program": null,
    "web_price": "DEFAULT",
    "web_stock": "HAVE",
    "group": "GROUP1",
    "unit": "hộp",
    "web_volume": null,
    "date_expire": "2026-09-23",
    "time_lock": "2025-01-11 17:19:23",
    "substitutes": "[]",
    "created_at": null,
    "updated_at": "2025-03-12 17:19:23",
    "status_import": "OK",
    "old_price": 53000
  },
  {
    "id": 7163,
    "name": "A.t Desloratadin 2.5Mg Hộp 30 Ống X 5Ml An Thiên",
    "common_name": "Desloratadin 2.5Mg",
    "images": [
      "image/at-desloratadin-hop-30-ong-5ml-an-thien_16092597651624518176.jpg"
    ],
    "price": 67500,
    "order_up": 0,
    "price_2": 0,
    "retail_price": 0,
    "profit_percent": 6.29921,
    "suggest_web_price": 67500,
    "suggest_price": null,
    "min_invent": null,
    "est_imp": 0,
    "category_id": 36,
    "producer_id": 29,
    "weight": 0,
    "dv_id": 15,
    "area_id": 2,
    "min_quantity": null,
    "note": null,
    "note_other": "",
    "status": "OK",
    "web_show": "OK",
    "type": "COM",
    "classify": "hang_hoa",
    "buy_address": "422",
    "web_promotion": "NO",
    "promotional_program": null,
    "web_price": "DEFAULT",
    "web_stock": "HAVE",
    "group": "GROUP1",
    "unit": "Hộp",
    "web_volume": "Hộp 30 ống x 5ml",
    "date_expire": null,
    "time_lock": "2025-01-11 14:54:24",
    "substitutes": "[]",
    "created_at": "2021-06-20 13:02:55",
    "updated_at": "2025-03-12 14:54:25",
    "status_import": "OK",
    "old_price": 67500
  },
  {
    "id": 6151,
    "name": "A.t Desloratadin Siro Lọ 30Ml An Thiên",
    "common_name": null,
    "images": [
      "image/desloratadin-siro-30ml-an-thien_16092592451624412104.jpg"
    ],
    "price": 19300,
    "order_up": 0,
    "price_2": 0,
    "retail_price": 0,
    "profit_percent": 10.2857,
    "suggest_web_price": 19300,
    "suggest_price": null,
    "min_invent": null,
    "est_imp": 0,
    "category_id": 36,
    "producer_id": 29,
    "weight": 55,
    "dv_id": 16,
    "area_id": 1,
    "min_quantity": null,
    "note": null,
    "note_other": "",
    "status": "OK",
    "web_show": "OK",
    "type": "COM",
    "classify": "hang_hoa",
    "buy_address": null,
    "web_promotion": "NO",
    "promotional_program": null,
    "web_price": "DEFAULT",
    "web_stock": "HAVE",
    "group": "GROUP1",
    "unit": "Lọ",
    "web_volume": "Hộp 1 lọ 30ml",
    "date_expire": null,
    "time_lock": "2025-01-11 12:30:05",
    "substitutes": "[]",
    "created_at": "2021-06-20 13:02:54",
    "updated_at": "2025-03-12 12:30:04",
    "status_import": "OK",
    "old_price": 19300
  },
  {
    "id": 6152,
    "name": "A.t Desloratadin Siro Lọ 60Ml An Thiên",
    "common_name": null,
    "images": [
      "image/desloratadin-siro-60ml-an-thien_16092592451624412129.jpg"
    ],
    "price": 24300,
    "order_up": 0,
    "price_2": 0,
    "retail_price": 0,
    "profit_percent": 10.4545,
    "suggest_web_price": 24300,
    "suggest_price": null,
    "min_invent": null,
    "est_imp": 0,
    "category_id": 36,
    "producer_id": 29,
    "weight": 0,
    "dv_id": 17,
    "area_id": 2,
    "min_quantity": null,
    "note": null,
    "note_other": "",
    "status": "OK",
    "web_show": "OK",
    "type": "COM",
    "classify": "hang_hoa",
    "buy_address": null,
    "web_promotion": "NO",
    "promotional_program": null,
    "web_price": "DEFAULT",
    "web_stock": "HAVE",
    "group": "GROUP1",
    "unit": "Chai",
    "web_volume": "Hộp 1 chai 60ml",
    "date_expire": "2026-10-20",
    "time_lock": "2025-01-11 15:34:43",
    "substitutes": "[]",
    "created_at": "2021-06-20 13:02:54",
    "updated_at": "2025-03-12 15:34:42",
    "status_import": "OK",
    "old_price": 24300
  },
  {
    "id": 9342,
    "name": "A.t Diosmectit 3G Hộp 30 Gói X 3,5G An Thiên",
    "common_name": null,
    "images": ["image/name12941-4166118861627961334.png"],
    "price": 64000,
    "order_up": 0,
    "price_2": 0,
    "retail_price": 0,
    "profit_percent": null,
    "suggest_web_price": 64000,
    "suggest_price": null,
    "min_invent": null,
    "est_imp": 0,
    "category_id": 34,
    "producer_id": 29,
    "weight": 157,
    "dv_id": 7131,
    "area_id": 4,
    "min_quantity": null,
    "note": null,
    "note_other": "",
    "status": "OK",
    "web_show": "OK",
    "type": "COM",
    "classify": "hang_hoa",
    "buy_address": null,
    "web_promotion": "NO",
    "promotional_program": null,
    "web_price": "DEFAULT",
    "web_stock": "HAVE",
    "group": "GROUP1",
    "unit": "Hộp",
    "web_volume": "Hộp 30 gói x 3,5 gram",
    "date_expire": null,
    "time_lock": "2025-01-09 08:43:53",
    "substitutes": "[]",
    "created_at": "2021-08-03 04:34:22",
    "updated_at": "2025-03-12 00:02:02",
    "status_import": "OK",
    "old_price": 64000
  },
  {
    "id": 9344,
    "name": "A.t Domperidon 5Mg Hộp 30 Gói X 5Ml An Thiên",
    "common_name": "Domperidon 5Mg",
    "images": ["image/name12939-1167230331627961444.png"],
    "price": 29800,
    "order_up": 0,
    "price_2": 0,
    "retail_price": 0,
    "profit_percent": 7.4261,
    "suggest_web_price": 29800,
    "suggest_price": null,
    "min_invent": null,
    "est_imp": 0,
    "category_id": 34,
    "producer_id": 29,
    "weight": 0,
    "dv_id": 18,
    "area_id": 2,
    "min_quantity": null,
    "note": null,
    "note_other": "",
    "status": "OK",
    "web_show": "OK",
    "type": "COM",
    "classify": "hang_hoa",
    "buy_address": null,
    "web_promotion": "NO",
    "promotional_program": null,
    "web_price": "DEFAULT",
    "web_stock": "HAVE",
    "group": "GROUP1",
    "unit": "Hộp",
    "web_volume": "Hộp 30 gói x 5ml",
    "date_expire": null,
    "time_lock": "2025-01-11 15:04:40",
    "substitutes": "[]",
    "created_at": "2021-08-03 04:34:22",
    "updated_at": "2025-03-12 15:04:39",
    "status_import": "OK",
    "old_price": 29800
  },
  {
    "id": 9343,
    "name": "A.t Domperidon 5Mg Hộp 30 Ống X 5Ml An Thiên",
    "common_name": null,
    "images": ["image/name14440-9126928471627961407.png"],
    "price": 29000,
    "order_up": 0,
    "price_2": 0,
    "retail_price": 0,
    "profit_percent": 4.54218,
    "suggest_web_price": 29000,
    "suggest_price": null,
    "min_invent": null,
    "est_imp": 0,
    "category_id": 34,
    "producer_id": 29,
    "weight": 220,
    "dv_id": null,
    "area_id": 1,
    "min_quantity": null,
    "note": null,
    "note_other": "",
    "status": "OK",
    "web_show": "OK",
    "type": "COM",
    "classify": "hang_hoa",
    "buy_address": null,
    "web_promotion": "NO",
    "promotional_program": null,
    "web_price": "DEFAULT",
    "web_stock": "HAVE",
    "group": "GROUP1",
    "unit": "Hộp",
    "web_volume": "Hộp 30 ống x 5ml",
    "date_expire": null,
    "time_lock": "2025-01-09 13:22:51",
    "substitutes": "[]",
    "created_at": "2021-08-03 04:34:22",
    "updated_at": "2025-03-12 00:02:02",
    "status_import": "OK",
    "old_price": 29000
  },
  {
    "id": 9346,
    "name": "A.t Entecavir 0.5Mg Hộp 3 Vỉ X 10 Viên Nén An Thiên",
    "common_name": null,
    "images": ["image/name11062-772147741627961502.png"],
    "price": 164500,
    "order_up": 0,
    "price_2": 0,
    "retail_price": 0,
    "profit_percent": null,
    "suggest_web_price": null,
    "suggest_price": null,
    "min_invent": null,
    "est_imp": 0,
    "category_id": 31,
    "producer_id": 29,
    "weight": 0,
    "dv_id": 19,
    "area_id": 3,
    "min_quantity": null,
    "note": null,
    "note_other": "",
    "status": "OK",
    "web_show": "OK",
    "type": "COM",
    "classify": "hang_hoa",
    "buy_address": null,
    "web_promotion": "NO",
    "promotional_program": null,
    "web_price": "DEFAULT",
    "web_stock": "HAVE",
    "group": "GROUP1",
    "unit": "Hộp",
    "web_volume": "Hộp 3 vỉ x 10 viên",
    "date_expire": "2026-08-01",
    "time_lock": "2025-01-11 10:24:40",
    "substitutes": "[]",
    "created_at": "2021-08-03 04:34:22",
    "updated_at": "2025-03-12 10:24:39",
    "status_import": "OK",
    "old_price": 164500
  },
  {
    "id": 20447,
    "name": "A.t Flu",
    "common_name": null,
    "images": ["image/4b7a585116b5a7ebfea41741765008.jpg"],
    "price": 165000,
    "order_up": 0,
    "price_2": 0,
    "retail_price": 0,
    "profit_percent": null,
    "suggest_web_price": null,
    "suggest_price": null,
    "min_invent": null,
    "est_imp": null,
    "category_id": null,
    "producer_id": null,
    "weight": 0,
    "dv_id": null,
    "area_id": null,
    "min_quantity": null,
    "note": null,
    "note_other": null,
    "status": "OK",
    "web_show": "OK",
    "type": "COM",
    "classify": "hang_hoa",
    "buy_address": null,
    "web_promotion": "NO",
    "promotional_program": null,
    "web_price": "DEFAULT",
    "web_stock": "HAVE",
    "group": "GROUP1",
    "unit": "hộp",
    "web_volume": null,
    "date_expire": null,
    "time_lock": null,
    "substitutes": "[]",
    "created_at": null,
    "updated_at": "2025-03-12 14:36:48",
    "status_import": "OK",
    "old_price": 165000
  },
  {
    "id": 6822,
    "name": "A.t Ibuprofen 100Mg Hộp 30 Ống X 5Ml An Thiên",
    "common_name": null,
    "images": ["image/at-ibuprofen-ong-5ml_16092596841624440757.jpg"],
    "price": 65000,
    "order_up": 0,
    "price_2": 0,
    "retail_price": 0,
    "profit_percent": 2.3622,
    "suggest_web_price": 65000,
    "suggest_price": null,
    "min_invent": null,
    "est_imp": 0,
    "category_id": 27,
    "producer_id": 29,
    "weight": 0,
    "dv_id": 22,
    "area_id": 2,
    "min_quantity": null,
    "note": null,
    "note_other": "",
    "status": "OK",
    "web_show": "OK",
    "type": "COM",
    "classify": "hang_hoa",
    "buy_address": null,
    "web_promotion": "NO",
    "promotional_program": null,
    "web_price": "DEFAULT",
    "web_stock": "HAVE",
    "group": "GROUP1",
    "unit": "Hộp",
    "web_volume": "Hộp 30 ống x 5ml",
    "date_expire": null,
    "time_lock": "2025-01-11 17:06:28",
    "substitutes": "[]",
    "created_at": "2021-06-20 13:02:55",
    "updated_at": "2025-03-12 17:06:28",
    "status_import": "OK",
    "old_price": 65000
  },
  {
    "id": 9350,
    "name": "A.t Ibuprofen 100Mg Siro Lọ 60Ml An Thiên",
    "common_name": null,
    "images": ["image/name2589-3832608501627961653.png"],
    "price": 19800,
    "order_up": 0,
    "price_2": 0,
    "retail_price": 0,
    "profit_percent": 10,
    "suggest_web_price": 19800,
    "suggest_price": null,
    "min_invent": null,
    "est_imp": 0,
    "category_id": 27,
    "producer_id": 29,
    "weight": 0,
    "dv_id": 23,
    "area_id": 2,
    "min_quantity": null,
    "note": null,
    "note_other": "",
    "status": "OK",
    "web_show": "OK",
    "type": "COM",
    "classify": "hang_hoa",
    "buy_address": null,
    "web_promotion": "NO",
    "promotional_program": null,
    "web_price": "DEFAULT",
    "web_stock": "HAVE",
    "group": "GROUP1",
    "unit": "Chai",
    "web_volume": "Chai 60ml",
    "date_expire": "2026-07-01",
    "time_lock": "2025-01-11 16:03:24",
    "substitutes": "[]",
    "created_at": "2021-08-03 04:34:22",
    "updated_at": "2025-03-12 16:03:23",
    "status_import": "OK",
    "old_price": 19800
  },
  {
    "id": 9348,
    "name": "A.T Ibuprofen Syrup 100mg/5ml hộp 30 ống nhựa x 10ml An Thiên",
    "common_name": null,
    "images": [
      "image/z3595555092776_86bc8eea6c75481791ef33179deace3c1658822005.jpg"
    ],
    "price": 77000,
    "order_up": 0,
    "price_2": 0,
    "retail_price": 0,
    "profit_percent": 5.47945,
    "suggest_web_price": 77000,
    "suggest_price": null,
    "min_invent": null,
    "est_imp": 0,
    "category_id": 27,
    "producer_id": 29,
    "weight": 0,
    "dv_id": 25,
    "area_id": 2,
    "min_quantity": null,
    "note": "At Ibuprofen( H/30O/5Ml)",
    "note_other": "",
    "status": "OK",
    "web_show": "OK",
    "type": "COM",
    "classify": "hang_hoa",
    "buy_address": null,
    "web_promotion": "NO",
    "promotional_program": null,
    "web_price": "DEFAULT",
    "web_stock": "HAVE",
    "group": "GROUP1",
    "unit": "Hộp",
    "web_volume": "Hộp 30 ống x 10ml",
    "date_expire": null,
    "time_lock": "2025-01-11 11:34:14",
    "substitutes": null,
    "created_at": "2021-08-03 04:34:22",
    "updated_at": "2025-03-12 11:34:13",
    "status_import": "OK",
    "old_price": 77000
  },
  {
    "id": 7153,
    "name": "A.t Loratadin 10Mg Hộp 10 Vỉ X 10 Viên Nén An Thiên",
    "common_name": "Lora An Thiên, At Lora Vỉ",
    "images": ["image/7F2A8AE4-5AB4-465B-9132-0D8B2837F37C1648883153.jpeg"],
    "price": 22000,
    "order_up": 0,
    "price_2": 0,
    "retail_price": 0,
    "profit_percent": 9.12698,
    "suggest_web_price": 22000,
    "suggest_price": null,
    "min_invent": null,
    "est_imp": 0,
    "category_id": 36,
    "producer_id": 29,
    "weight": 0,
    "dv_id": 26,
    "area_id": 2,
    "min_quantity": null,
    "note": "1 kiện 144 hộp",
    "note_other": "",
    "status": "OK",
    "web_show": "OK",
    "type": "COM",
    "classify": "hang_hoa",
    "buy_address": "422",
    "web_promotion": "NO",
    "promotional_program": null,
    "web_price": "DEFAULT",
    "web_stock": "HAVE",
    "group": "GROUP1",
    "unit": "Hộp",
    "web_volume": "Hộp 10 vỉ x10 viên",
    "date_expire": null,
    "time_lock": "2025-01-11 17:01:24",
    "substitutes": "[]",
    "created_at": "2021-06-20 13:02:55",
    "updated_at": "2025-03-12 17:01:23",
    "status_import": "OK",
    "old_price": 22000
  },
  {
    "id": 14827,
    "name": "A.t Loratadin 10Mg Lọ 100 Viên Nén An Thiên",
    "common_name": "At Lora Lọ",
    "images": ["image/lra1648184954.png"],
    "price": 22300,
    "order_up": 0,
    "price_2": 0,
    "retail_price": 0,
    "profit_percent": 10.6151,
    "suggest_web_price": 22300,
    "suggest_price": null,
    "min_invent": null,
    "est_imp": 0,
    "category_id": 36,
    "producer_id": 29,
    "weight": 0,
    "dv_id": 27,
    "area_id": 2,
    "min_quantity": null,
    "note": null,
    "note_other": "",
    "status": "OK",
    "web_show": "OK",
    "type": "COM",
    "classify": "hang_hoa",
    "buy_address": "422",
    "web_promotion": "NO",
    "promotional_program": null,
    "web_price": "DEFAULT",
    "web_stock": "HAVE",
    "group": "GROUP1",
    "unit": "Lọ",
    "web_volume": "Hộp 10 vỉ x 10 viên",
    "date_expire": null,
    "time_lock": "2025-01-11 17:06:28",
    "substitutes": "[]",
    "created_at": null,
    "updated_at": "2025-03-12 17:06:28",
    "status_import": "OK",
    "old_price": 22300
  },
  {
    "id": 19882,
    "name": "A.t Magnesi B6 Plus Hỗn Dịch Uống Hộp 30 Gói X 10Ml - An Thiên",
    "common_name": null,
    "images": ["image/Magnesi B61729586394.jpg"],
    "price": 161500,
    "order_up": 0,
    "price_2": 0,
    "retail_price": 0,
    "profit_percent": null,
    "suggest_web_price": null,
    "suggest_price": null,
    "min_invent": null,
    "est_imp": 0,
    "category_id": 33,
    "producer_id": 29,
    "weight": 0,
    "dv_id": null,
    "area_id": 2,
    "min_quantity": null,
    "note": null,
    "note_other": "",
    "status": "OK",
    "web_show": "OK",
    "type": "COM",
    "classify": "hang_hoa",
    "buy_address": null,
    "web_promotion": null,
    "promotional_program": null,
    "web_price": null,
    "web_stock": null,
    "group": "GROUP1",
    "unit": "Hộp",
    "web_volume": null,
    "date_expire": null,
    "time_lock": "2024-12-16 08:33:40",
    "substitutes": "[]",
    "created_at": null,
    "updated_at": "2025-03-12 00:02:02",
    "status_import": "OK",
    "old_price": 161500
  },
  {
    "id": 17841,
    "name": "A.t Mometasone Furoate 0.1% An Thiên 10G",
    "common_name": null,
    "images": ["image/at1690364638.jpg"],
    "price": 44500,
    "order_up": 0,
    "price_2": 0,
    "retail_price": 0,
    "profit_percent": null,
    "suggest_web_price": null,
    "suggest_price": null,
    "min_invent": null,
    "est_imp": 0,
    "category_id": 38,
    "producer_id": 29,
    "weight": 0,
    "dv_id": null,
    "area_id": 4,
    "min_quantity": null,
    "note": null,
    "note_other": "",
    "status": "OK",
    "web_show": "OK",
    "type": "COM",
    "classify": "hang_hoa",
    "buy_address": null,
    "web_promotion": "NO",
    "promotional_program": null,
    "web_price": "DEFAULT",
    "web_stock": "HAVE",
    "group": "GROUP1",
    "unit": "tuýp",
    "web_volume": null,
    "date_expire": null,
    "time_lock": "2025-01-05 09:01:05",
    "substitutes": "[]",
    "created_at": null,
    "updated_at": "2025-03-12 00:02:02",
    "status_import": "OK",
    "old_price": 44500
  },
  {
    "id": 16218,
    "name": "A.t Pantoprazol 40Mg Tab An Thiên (H/100V)",
    "common_name": null,
    "images": ["image/79E1B1A8-432C-47F5-89E2-7874E5F303E51654935630.jpeg"],
    "price": 77000,
    "order_up": 0,
    "price_2": 0,
    "retail_price": 0,
    "profit_percent": 4.05405,
    "suggest_web_price": 77000,
    "suggest_price": null,
    "min_invent": null,
    "est_imp": 0,
    "category_id": 34,
    "producer_id": 29,
    "weight": 0,
    "dv_id": null,
    "area_id": 2,
    "min_quantity": null,
    "note": null,
    "note_other": "",
    "status": "OK",
    "web_show": "OK",
    "type": "COM",
    "classify": "hang_hoa",
    "buy_address": null,
    "web_promotion": "NO",
    "promotional_program": null,
    "web_price": "DEFAULT",
    "web_stock": "HAVE",
    "group": "GROUP1",
    "unit": "hộp",
    "web_volume": "Hộp 10 vỉ x 10 viên",
    "date_expire": null,
    "time_lock": "2025-01-10 14:47:47",
    "substitutes": null,
    "created_at": null,
    "updated_at": "2025-03-12 00:02:02",
    "status_import": "OK",
    "old_price": 77000
  },
  {
    "id": 16475,
    "name": "A.t Pantoprazol 40Mg Tiêm An Thiên (H/3Ố/10Ml)",
    "common_name": "Pantoprazol 40Mg",
    "images": ["image/9a046332c1ab10f549ba1687483465.jpg"],
    "price": 37000,
    "order_up": 0,
    "price_2": 0,
    "retail_price": 0,
    "profit_percent": null,
    "suggest_web_price": 79500,
    "suggest_price": null,
    "min_invent": null,
    "est_imp": 0,
    "category_id": 34,
    "producer_id": 29,
    "weight": 0,
    "dv_id": null,
    "area_id": 4,
    "min_quantity": null,
    "note": null,
    "note_other": "",
    "status": "OK",
    "web_show": "OK",
    "type": "COM",
    "classify": "hang_hoa",
    "buy_address": null,
    "web_promotion": "NO",
    "promotional_program": null,
    "web_price": "DEFAULT",
    "web_stock": "HAVE",
    "group": "GROUP1",
    "unit": "Hộp",
    "web_volume": "Hộp x 3 ống x 10 ml",
    "date_expire": null,
    "time_lock": "2025-01-10 14:59:16",
    "substitutes": "[]",
    "created_at": null,
    "updated_at": "2025-03-12 00:02:02",
    "status_import": "OK",
    "old_price": 37000
  },
  {
    "id": 16698,
    "name": "A.t Silymarin 117Mg Hộp 3 Vỉ X 10 Viên An Thiên",
    "common_name": "Có Dấu",
    "images": ["image/3e5cbe77584c9f12c65d1665716723.jpg"],
    "price": 132000,
    "order_up": 0,
    "price_2": 0,
    "retail_price": 0,
    "profit_percent": null,
    "suggest_web_price": 115000,
    "suggest_price": null,
    "min_invent": null,
    "est_imp": 0,
    "category_id": 31,
    "producer_id": 29,
    "weight": 0,
    "dv_id": 28,
    "area_id": 2,
    "min_quantity": null,
    "note": null,
    "note_other": "",
    "status": "OK",
    "web_show": "OK",
    "type": "COM",
    "classify": "hang_hoa",
    "buy_address": null,
    "web_promotion": "NO",
    "promotional_program": null,
    "web_price": "DEFAULT",
    "web_stock": "HAVE",
    "group": "GROUP1",
    "unit": "hộp",
    "web_volume": null,
    "date_expire": "2026-09-10",
    "time_lock": "2025-01-10 11:54:35",
    "substitutes": "[]",
    "created_at": null,
    "updated_at": "2025-03-12 00:02:02",
    "status_import": "OK",
    "old_price": 132000
  },
  {
    "id": 16680,
    "name": "A.t Sucralfate 1000Mg Hộp 20 Gói X 5G An Thiên",
    "common_name": null,
    "images": ["image/7158b17e0752c00c99431665543731.jpg"],
    "price": 37500,
    "order_up": 0,
    "price_2": 0,
    "retail_price": 0,
    "profit_percent": 6.30758,
    "suggest_web_price": 37500,
    "suggest_price": null,
    "min_invent": null,
    "est_imp": 0,
    "category_id": 34,
    "producer_id": 29,
    "weight": 0,
    "dv_id": 30,
    "area_id": 2,
    "min_quantity": null,
    "note": null,
    "note_other": "",
    "status": "OK",
    "web_show": "OK",
    "type": "COM",
    "classify": "hang_hoa",
    "buy_address": null,
    "web_promotion": "NO",
    "promotional_program": null,
    "web_price": "DEFAULT",
    "web_stock": "HAVE",
    "group": "GROUP1",
    "unit": "hộp",
    "web_volume": null,
    "date_expire": null,
    "time_lock": "2025-01-11 15:58:10",
    "substitutes": "[]",
    "created_at": null,
    "updated_at": "2025-03-12 15:58:08",
    "status_import": "OK",
    "old_price": 37500
  },
  {
    "id": 19812,
    "name": "A.t Urea 20% Tuýp 20G - An Thiên",
    "common_name": null,
    "images": ["image/Urea1728530479.jpg"],
    "price": 51500,
    "order_up": 0,
    "price_2": 0,
    "retail_price": 0,
    "profit_percent": null,
    "suggest_web_price": null,
    "suggest_price": null,
    "min_invent": null,
    "est_imp": 0,
    "category_id": 41,
    "producer_id": 29,
    "weight": 0,
    "dv_id": null,
    "area_id": 4,
    "min_quantity": null,
    "note": null,
    "note_other": "",
    "status": "OK",
    "web_show": "OK",
    "type": "COM",
    "classify": "hang_hoa",
    "buy_address": null,
    "web_promotion": null,
    "promotional_program": null,
    "web_price": null,
    "web_stock": null,
    "group": "GROUP1",
    "unit": "Tuýp",
    "web_volume": null,
    "date_expire": null,
    "time_lock": "2025-01-05 16:45:26",
    "substitutes": "[]",
    "created_at": null,
    "updated_at": "2025-03-12 00:02:02",
    "status_import": "OK",
    "old_price": 51500
  }
]
